vklancer/__init__.py
vklancer/api.py
vklancer/utils.py
vklancer-1.4.0.dist-info/DESCRIPTION.rst
vklancer-1.4.0.dist-info/METADATA
vklancer-1.4.0.dist-info/RECORD
vklancer-1.4.0.dist-info/WHEEL
vklancer-1.4.0.dist-info/metadata.json
vklancer-1.4.0.dist-info/top_level.txt
